brave_torch/__init__.py
brave_torch/llm.py
brave_torch/main.py
brave_torch-4.7.9.dist-info/LICENSE
brave_torch-4.7.9.dist-info/WHEEL
brave_torch-4.7.9.dist-info/METADATA
brave_torch-4.7.9.dist-info/RECORD
