Metadata-Version: 2.1
Name: brave-torch
Version: 4.7.9
Summary: Swarms - Pytorch
Home-page: https://github.com/kyegomez/BRAVE-ViT-Swarm
License: MIT
Keywords: artificial intelligence,deep learning,optimizers,Prompt Engineering,swarms,agents
Author: Kye Gomez
Author-email: kye@apac.ai
Requires-Python: >=3.9,<4.0
Classifier: Development Status :: 4 - Beta
Classifier: Intended Audience :: Developers
Classifier: License :: OSI Approved :: MIT License
Classifier: Programming Language :: Python :: 3
Classifier: Programming Language :: Python :: 3.9
Classifier: Programming Language :: Python :: 3.10
Classifier: Programming Language :: Python :: 3.11
Classifier: Programming Language :: Python :: 3.10
Classifier: Topic :: Scientific/Engineering :: Artificial Intelligence
Requires-Dist: einops
Requires-Dist: einops_exts
Requires-Dist: torch (>=2.1.1,<3.0)
Requires-Dist: zetascale
Project-URL: Documentation, https://swarms.apac.ai
Project-URL: Repository, https://github.com/kyegomez/BRAVE-ViT-Swarm
